odoo8_addon_website_event_sale_legal-8.0.1.0.0.99.dev3-py2.7-nspkg.pth
odoo8_addon_website_event_sale_legal-8.0.1.0.0.99.dev3.dist-info/top_level.txt
odoo8_addon_website_event_sale_legal-8.0.1.0.0.99.dev3.dist-info/WHEEL
odoo8_addon_website_event_sale_legal-8.0.1.0.0.99.dev3.dist-info/RECORD
odoo8_addon_website_event_sale_legal-8.0.1.0.0.99.dev3.dist-info/metadata.json
odoo8_addon_website_event_sale_legal-8.0.1.0.0.99.dev3.dist-info/DESCRIPTION.rst
odoo8_addon_website_event_sale_legal-8.0.1.0.0.99.dev3.dist-info/METADATA
odoo8_addon_website_event_sale_legal-8.0.1.0.0.99.dev3.dist-info/namespace_packages.txt
odoo_addons/website_event_sale_legal/__openerp__.py
odoo_addons/website_event_sale_legal/__init__.py
odoo_addons/website_event_sale_legal/README.rst
odoo_addons/website_event_sale_legal/models/event_event.py
odoo_addons/website_event_sale_legal/models/__init__.py
odoo_addons/website_event_sale_legal/models/legal_term.py
odoo_addons/website_event_sale_legal/i18n/es.po
odoo_addons/website_event_sale_legal/views/event_event_view.xml
odoo_addons/website_event_sale_legal/views/templates.xml
odoo_addons/website_event_sale_legal/views/legal_term_view.xml
odoo_addons/website_event_sale_legal/controllers/main.py
odoo_addons/website_event_sale_legal/controllers/__init__.py
odoo_addons/website_event_sale_legal/tests/test_event.py
odoo_addons/website_event_sale_legal/tests/__init__.py
odoo_addons/website_event_sale_legal/static/description/icon.png
