Metadata-Version: 2.0
Name: odoo8-addon-website-event-sale-legal
Version: 8.0.1.0.0.99.dev3
Summary: Make attendees to accept legal terms per event
Home-page: http://www.antiun.com
Author: UNKNOWN
Author-email: UNKNOWN
License: AGPL-3
Platform: UNKNOWN
Requires-Dist: odoo (<9.0a,>=8.0a)
Requires-Dist: odoo8-addon-website-sale-product-legal
Classifier: Programming Language :: Python :: 2.7
Classifier: Framework :: Odoo
Classifier: License :: OSI Approved :: GNU Affero General Public License v3
